ethermine/__init__.py
ethermine/ethermine.py
ethermine-0.1.0.dist-info/LICENSE.txt
ethermine-0.1.0.dist-info/METADATA
ethermine-0.1.0.dist-info/WHEEL
ethermine-0.1.0.dist-info/top_level.txt
ethermine-0.1.0.dist-info/RECORD
